conda_store/__init__.py
conda_store/__main__.py
conda_store/api.py
conda_store/exception.py
conda_store/_internal/__init__.py
conda_store/_internal/auth.py
conda_store/_internal/cli.py
conda_store/_internal/runner.py
conda_store/_internal/utils.py
conda_store-2025.2.1.dist-info/METADATA
conda_store-2025.2.1.dist-info/WHEEL
conda_store-2025.2.1.dist-info/entry_points.txt
conda_store-2025.2.1.dist-info/licenses/LICENSE
conda_store-2025.2.1.dist-info/RECORD
